shinherpro/Account.py
shinherpro/TYAI.py
shinherpro/__init__.py
shinherpro/chormeDriver.py
shinherpro/html.py
shinherpro/logSave.py
shinherpro/serverLog.py
shinherpro/vfcModel.py
shinherpro-1.7.3.dist-info/METADATA
shinherpro-1.7.3.dist-info/WHEEL
shinherpro-1.7.3.dist-info/top_level.txt
shinherpro-1.7.3.dist-info/RECORD
