Metadata-Version: 2.1
Name: shinherpro
Version: 1.7.3
Summary: shinher-pro 1.7.3
Author: Yihuan
Author-email: ivan17.lai@gmail.com
Requires-Dist: selenium
Requires-Dist: beautifulsoup4
Requires-Dist: keras
Requires-Dist: opencv-python
Requires-Dist: Pillow
Requires-Dist: tensorflow
Requires-Dist: requests
Requires-Dist: numpy
